NetkillerArchitect/README.md
NetkillerArchitect/__init__.py
NetkillerArchitect/__main__.py
NetkillerArchitect/file.epub
NetkillerArchitect/index.html
NetkillerArchitect/css/__init__.py
NetkillerArchitect/css/annotations.css
NetkillerArchitect/css/main.css
NetkillerArchitect/css/normalize.css
NetkillerArchitect/css/popup.css
NetkillerArchitect/font/__init__.py
NetkillerArchitect/font/fontello.eot
NetkillerArchitect/font/fontello.svg
NetkillerArchitect/font/fontello.ttf
NetkillerArchitect/font/fontello.woff
NetkillerArchitect/img/__init__.py
NetkillerArchitect/img/annotator-glyph-sprite.png
NetkillerArchitect/img/annotator-icon-sprite.png
NetkillerArchitect/img/apple-touch-icon.png
NetkillerArchitect/img/cancelfullscreen.png
NetkillerArchitect/img/close.png
NetkillerArchitect/img/fullscreen.png
NetkillerArchitect/img/loader.gif
NetkillerArchitect/img/menu-icon.png
NetkillerArchitect/img/save.png
NetkillerArchitect/img/saved.png
NetkillerArchitect/img/settings-s.png
NetkillerArchitect/img/settings.png
NetkillerArchitect/img/star.png
NetkillerArchitect/js/__init__.py
NetkillerArchitect/js/epub.js
NetkillerArchitect/js/epub.min.js
NetkillerArchitect/js/epub.min.map
NetkillerArchitect/js/hooks.min.js
NetkillerArchitect/js/hooks.min.map
NetkillerArchitect/js/reader.js
NetkillerArchitect/js/reader.js.map
NetkillerArchitect/js/reader.min.js
NetkillerArchitect/js/reader.min.map
NetkillerArchitect/js/hooks/__init__.py
NetkillerArchitect/js/hooks/extensions/__init__.py
NetkillerArchitect/js/hooks/extensions/highlight.js
NetkillerArchitect/js/libs/__init__.py
NetkillerArchitect/js/libs/jquery.min.js
NetkillerArchitect/js/libs/localforage.min.js
NetkillerArchitect/js/libs/screenfull.js
NetkillerArchitect/js/libs/screenfull.min.js
NetkillerArchitect/js/libs/zip.min.js
NetkillerArchitect/js/plugins/__init__.py
NetkillerArchitect/js/plugins/hypothesis.js
NetkillerArchitect/js/plugins/search.js
netkiller_architect-2024.3.5.0.dist-info/METADATA
netkiller_architect-2024.3.5.0.dist-info/WHEEL
netkiller_architect-2024.3.5.0.dist-info/entry_points.txt
netkiller_architect-2024.3.5.0.dist-info/top_level.txt
netkiller_architect-2024.3.5.0.dist-info/RECORD
